pyleb128/__init__.py
pyleb128/_base.py
pyleb128/_sleb.py
pyleb128/_uleb.py
pyleb128-0.2.4.dist-info/LICENSE
pyleb128-0.2.4.dist-info/METADATA
pyleb128-0.2.4.dist-info/WHEEL
pyleb128-0.2.4.dist-info/RECORD
