Metadata-Version: 2.1
Name: pyleb128
Version: 0.2.4
Summary: Powerful little-endian base-128 encoding/decoding library for Python 3.
Home-page: https://github.com/yntha/pyleb128
License: GPL-3.0-or-later
Author: yntha
Author-email: bguznvjk@gmail.com
Requires-Python: >=3.11,<4.0
Classifier: License :: OSI Approved :: GNU General Public License v3 or later (GPLv3+)
Classifier: Programming Language :: Python :: 3
Classifier: Programming Language :: Python :: 3.11
